medcat/__init__.py
medcat/cat.py
medcat/cdb.py
medcat/cdb_maker.py
medcat/config.py
medcat/config_meta_cat.py
medcat/config_transformers_ner.py
medcat/meta_cat.py
medcat/pipe.py
medcat/vocab.py
medcat/cogstack/__init__.py
medcat/cogstack/cogstack_conn.py
medcat/datasets/__init__.py
medcat/datasets/data_collator.py
medcat/datasets/helpers.py
medcat/datasets/medcat_annotations.py
medcat/datasets/patient_concept_stream.py
medcat/datasets/transformers_ner.py
medcat/linking/__init__.py
medcat/linking/context_based_linker.py
medcat/linking/vector_context_model.py
medcat/neo/__init__.py
medcat/neo/data_preparation.py
medcat/neo/neo_connector.py
medcat/ner/__init__.py
medcat/ner/transformers_ner.py
medcat/ner/vocab_based_annotator.py
medcat/ner/vocab_based_ner.py
medcat/pipeline/__init__.py
medcat/pipeline/pipe_runner.py
medcat/preprocessing/__init__.py
medcat/preprocessing/cleaners.py
medcat/preprocessing/iterators.py
medcat/preprocessing/taggers.py
medcat/preprocessing/tokenizers.py
medcat/tokenizers/__init__.py
medcat/tokenizers/meta_cat_tokenizers.py
medcat/tokenizers/transformers_ner.py
medcat/utils/__init__.py
medcat/utils/cdb_helpers.py
medcat/utils/checkpoint.py
medcat/utils/clinical_note_splitter.py
medcat/utils/data_utils.py
medcat/utils/decorators.py
medcat/utils/ethnicity_map.py
medcat/utils/filters.py
medcat/utils/hasher.py
medcat/utils/helpers.py
medcat/utils/make_vocab.py
medcat/utils/matutils.py
medcat/utils/medmentions.py
medcat/utils/ml_utils.py
medcat/utils/model_creator.py
medcat/utils/normalizers.py
medcat/utils/other.py
medcat/utils/postprocessing.py
medcat/utils/preprocess_snomed.py
medcat/utils/repair_cdb.py
medcat/utils/meta_cat/__init__.py
medcat/utils/meta_cat/data_utils.py
medcat/utils/meta_cat/ml_utils.py
medcat/utils/meta_cat/models.py
medcat/utils/ner/__init__.py
medcat/utils/ner/helpers.py
medcat/utils/ner/metrics.py
zensols.medcat-1.3.0.dist-info/LICENSE
zensols.medcat-1.3.0.dist-info/METADATA
zensols.medcat-1.3.0.dist-info/WHEEL
zensols.medcat-1.3.0.dist-info/top_level.txt
zensols.medcat-1.3.0.dist-info/RECORD
