Metadata-Version: 2.1
Name: zensols.medcat
Version: 1.3.0
Summary: Concept annotation tool for Electronic Health Records
Home-page: https://github.com/CogStack/MedCAT
Author: w-is-h
Author-email: w.kraljevic@gmail.com
Classifier: Programming Language :: Python :: 3
Classifier: Programming Language :: Python :: 3.7
Classifier: Programming Language :: Python :: 3.8
Classifier: Programming Language :: Python :: 3.9
Classifier: License :: OSI Approved :: MIT License
Classifier: Operating System :: OS Independent
License-File: LICENSE
Requires-Dist: numpy (>=1.21.4)
Requires-Dist: pandas (<=1.4.2,>=1.1.5)
Requires-Dist: gensim (~=4.1.2)
Requires-Dist: scipy (<=1.8.1,>=1.5.4)
Requires-Dist: transformers (~=4.19.2)
Requires-Dist: torch (>=1.0)
Requires-Dist: tqdm (>=4.27)
Requires-Dist: sklearn (~=0.0)
Requires-Dist: elasticsearch (<8.0.0,>=7.10)
Requires-Dist: dill (~=0.3.4)
Requires-Dist: datasets (~=2.2.2)
Requires-Dist: jsonpickle (~=2.0.0)
Requires-Dist: psutil (<6.0.0,>=5.8.0)
Requires-Dist: multiprocess
Requires-Dist: py2neo (==2021.2.3)
Requires-Dist: aiofiles (~=0.8.0)
Requires-Dist: ipywidgets (~=7.6.5)
Requires-Dist: xxhash (==3.0.0)
Requires-Dist: blis (<=0.7.5)
Requires-Dist: click (<=8.0.4)
